nflnames/__init__.py
nflnames/players.py
nflnames/teams.py
nflnames/data/master_players.csv
scripts/__init__.py
scripts/update_master_players.py
nflnames-0.1.dist-info/LICENSE
nflnames-0.1.dist-info/METADATA
nflnames-0.1.dist-info/WHEEL
nflnames-0.1.dist-info/top_level.txt
nflnames-0.1.dist-info/RECORD
