Metadata-Version: 2.1
Name: nflnames
Version: 0.1
Summary: python library for standardizing NFL team and player names
Home-page: UNKNOWN
Author: Eric Truett
Author-email: eric@erictruett.com
License: Apache 2.0
Platform: UNKNOWN
